daedalus/__init__.py
daedalus/_maze.so
daedalus/test/__init__.py
daedalus/test/test_maze.py
pydaedalus-0.1.4.dist-info/DESCRIPTION.rst
pydaedalus-0.1.4.dist-info/METADATA
pydaedalus-0.1.4.dist-info/metadata.json
pydaedalus-0.1.4.dist-info/RECORD
pydaedalus-0.1.4.dist-info/top_level.txt
pydaedalus-0.1.4.dist-info/WHEEL
