Metadata-Version: 2.0
Name: pydaedalus
Version: 0.1.4
Summary: Python wrapper of Daedalus monochrome maze
Home-page: https://github.com/wroberts/pydaedalus
Author: Will Roberts
Author-email: wildwilhelm@gmail.com
License: GPLv2
Keywords: maze generation solving daedalus
Platform: UNKNOWN
Classifier: Development Status :: 3 - Alpha
Classifier: Intended Audience :: Developers
Classifier: Intended Audience :: Science/Research
Classifier: Topic :: Games/Entertainment :: Puzzle Games
Classifier: License :: OSI Approved :: GNU General Public License v2 (GPLv2)
Classifier: Programming Language :: Python :: 2
Classifier: Programming Language :: Python :: 2.7
Classifier: Programming Language :: Python :: 3
Classifier: Programming Language :: Python :: 3.2
Classifier: Programming Language :: Python :: 3.3
Classifier: Programming Language :: Python :: 3.4
Classifier: Programming Language :: Python :: 3.5
Classifier: Programming Language :: Python :: 3.6
